{"nodes": [{"id": "src_store_entries_ts", "label": "entries.ts", "file_type": "code", "source_file": "src/store/entries.ts", "source_location": "L1"}, {"id": "entries_maprow", "label": "mapRow()", "file_type": "code", "source_file": "src/store/entries.ts", "source_location": "L54"}, {"id": "entries_scopevisibilityclause", "label": "scopeVisibilityClause()", "file_type": "code", "source_file": "src/store/entries.ts", "source_location": "L80"}, {"id": "entries_getentrybyid", "label": "getEntryById()", "file_type": "code", "source_file": "src/store/entries.ts", "source_location": "L107"}, {"id": "entries_fetchentriesbyids", "label": "fetchEntriesByIds()", "file_type": "code", "source_file": "src/store/entries.ts", "source_location": "L134"}], "edges": [{"source": "src_store_entries_ts", "target": "bun_sqlite", "relation": "imports_from", "confidence": "EXTRACTED", "source_file": "src/store/entries.ts", "source_location": "L8", "weight": 1.0}, {"source": "src_store_entries_ts", "target": "entries_maprow", "relation": "contains", "confidence": "EXTRACTED", "source_file": "src/store/entries.ts", "source_location": "L54", "weight": 1.0}, {"source": "src_store_entries_ts", "target": "entries_scopevisibilityclause", "relation": "contains", "confidence": "EXTRACTED", "source_file": "src/store/entries.ts", "source_location": "L80", "weight": 1.0}, {"source": "src_store_entries_ts", "target": "entries_getentrybyid", "relation": "contains", "confidence": "EXTRACTED", "source_file": "src/store/entries.ts", "source_location": "L107", "weight": 1.0}, {"source": "src_store_entries_ts", "target": "entries_fetchentriesbyids", "relation": "contains", "confidence": "EXTRACTED", "source_file": "src/store/entries.ts", "source_location": "L134", "weight": 1.0}, {"source": "entries_getentrybyid", "target": "entries_scopevisibilityclause", "relation": "calls", "confidence": "EXTRACTED", "source_file": "src/store/entries.ts", "source_location": "L113", "weight": 1.0}, {"source": "entries_getentrybyid", "target": "entries_maprow", "relation": "calls", "confidence": "EXTRACTED", "source_file": "src/store/entries.ts", "source_location": "L127", "weight": 1.0}, {"source": "entries_fetchentriesbyids", "target": "entries_scopevisibilityclause", "relation": "calls", "confidence": "EXTRACTED", "source_file": "src/store/entries.ts", "source_location": "L144", "weight": 1.0}], "raw_calls": [{"caller_nid": "entries_getentrybyid", "callee": "get", "source_file": "src/store/entries.ts", "source_location": "L123"}, {"caller_nid": "entries_getentrybyid", "callee": "query", "source_file": "src/store/entries.ts", "source_location": "L123"}, {"caller_nid": "entries_fetchentriesbyids", "callee": "join", "source_file": "src/store/entries.ts", "source_location": "L142"}, {"caller_nid": "entries_fetchentriesbyids", "callee": "map", "source_file": "src/store/entries.ts", "source_location": "L142"}, {"caller_nid": "entries_fetchentriesbyids", "callee": "all", "source_file": "src/store/entries.ts", "source_location": "L155"}, {"caller_nid": "entries_fetchentriesbyids", "callee": "query", "source_file": "src/store/entries.ts", "source_location": "L155"}, {"caller_nid": "entries_fetchentriesbyids", "callee": "map", "source_file": "src/store/entries.ts", "source_location": "L157"}, {"caller_nid": "entries_fetchentriesbyids", "callee": "flatMap", "source_file": "src/store/entries.ts", "source_location": "L158"}]}